[
  {
    "elementType": "geometry",
    "stylers": [
      {
        "color": "#404040"
      }
    ]
  },
  {
    "elementType": "labels.icon",
    "stylers": [
      {
        "visibility": "off"
      }
    ]
  },
  {
    "elementType": "labels.text.fill",
    "stylers": [
      {
        "color": "#b5b5b5"
      }
    ]
  },
  {
    "elementType": "labels.text.stroke",
    "stylers": [
      {
        "color": "#212121"
      }
    ]
  },
  {
    "featureType": "administrative",
    "elementType": "geometry",
    "stylers": [
      {
        "color": "#757575"
      }
    ]
  },
  {
    "featureType": "administrative.country",
    "elementType": "labels.text.fill",
    "stylers": [
      {
        "color": "#cccccc"
      }
    ]
  },
  {
    "featureType": "administrative.land_parcel",
    "stylers": [
      {
        "color": "#757575"
      },
      {
        "visibility": "off"
      }
    ]
  },
  {
    "featureType": "administrative.locality",
    "elementType": "labels.text.fill",
    "stylers": [
      {
        "color": "#c4c4c4"
      }
    ]
  },
  {
    "featureType": "landscape",
    "stylers": [
      {
        "color": "#636363"
      }
    ]
  },
  {
    "featureType": "poi",
    "elementType": "labels.text.fill",
    "stylers": [
      {
        "color": "#757575"
      }
    ]
  },
  {
    "featureType": "poi.park",
    "elementType": "geometry",
    "stylers": [
      {
        "color": "#3d3d3d"
      }
    ]
  },
  {
    "featureType": "poi.park",
    "elementType": "labels.text.fill",
    "stylers": [
      {
        "color": "#c4c4c4"
      }
    ]
  },
  {
    "featureType": "poi.park",
    "elementType": "labels.text.stroke",
    "stylers": [
      {
        "color": "#1b1b1b"
      }
    ]
  },
  {
    "featureType": "road",
    "elementType": "geometry.fill",
    "stylers": [
      {
        "color": "#4f4f4f"
      }
    ]
  },
  {
    "featureType": "road",
    "elementType": "labels.text.fill",
    "stylers": [
      {
        "color": "#8a8a8a"
      }
    ]
  },
  {
    "featureType": "road.arterial",
    "elementType": "geometry",
    "stylers": [
      {
        "color": "#4d4d4d"
      }
    ]
  },
  {
    "featureType": "road.highway",
    "elementType": "geometry",
    "stylers": [
      {
        "color": "#575757"
      }
    ]
  },
  {
    "featureType": "road.highway.controlled_access",
    "elementType": "geometry",
    "stylers": [
      {
        "color": "#4e4e4e"
      }
    ]
  },
  {
    "featureType": "road.local",
    "elementType": "labels.text.fill",
    "stylers": [
      {
        "color": "#616161"
      }
    ]
  },
  {
    "featureType": "transit",
    "elementType": "labels.text.fill",
    "stylers": [
      {
        "color": "#ababab"
      }
    ]
  },
  {
    "featureType": "water",
    "stylers": [
      {
        "color": "#b8b8b8"
      }
    ]
  },
  {
    "featureType": "water",
    "elementType": "geometry",
    "stylers": [
      {
        "color": "#3d3d3d"
      }
    ]
  },
  {
    "featureType": "water",
    "elementType": "labels.text.fill",
    "stylers": [
      {
        "color": "#3d3d3d"
      }
    ]
  }
]